hoyowrapper/Genshin.py
hoyowrapper/Starrail.py
hoyowrapper/Tools.py
hoyowrapper/__init__.py
hoyowrapper/constants.py
hoyowrapper-0.1.2.dist-info/METADATA
hoyowrapper-0.1.2.dist-info/WHEEL
hoyowrapper-0.1.2.dist-info/top_level.txt
hoyowrapper-0.1.2.dist-info/RECORD
