Metadata-Version: 2.2
Name: hoyowrapper
Version: 0.1.2
Summary: A library for handling interactions with Hoyolab via Python.
Author: Guitarband
Author-email: preetish_choudhary@outlook.com
Classifier: Programming Language :: Python :: 3
Classifier: License :: OSI Approved :: MIT License
Classifier: Operating System :: OS Independent
Requires-Dist: requests
Requires-Dist: asyncio
Requires-Dist: pyppeteer
Dynamic: author
Dynamic: author-email
Dynamic: classifier
Dynamic: description
Dynamic: description-content-type
Dynamic: requires-dist
Dynamic: summary
